mallm/__init__.py
mallm/agents/__init__.py
mallm/agents/agent.py
mallm/agents/draftProposer.py
mallm/agents/judge.py
mallm/agents/panelist.py
mallm/coordinator.py
mallm/decision_protocols/__init__.py
mallm/decision_protocols/approval_voting.py
mallm/decision_protocols/consensus.py
mallm/decision_protocols/consensus_voting.py
mallm/decision_protocols/cumulative_voting.py
mallm/decision_protocols/judge.py
mallm/decision_protocols/protocol.py
mallm/decision_protocols/ranked_voting.py
mallm/decision_protocols/simple_voting.py
mallm/discussion_paradigms/__init__.py
mallm/discussion_paradigms/collective_refinement.py
mallm/discussion_paradigms/debate.py
mallm/discussion_paradigms/memory.py
mallm/discussion_paradigms/paradigm.py
mallm/discussion_paradigms/relay.py
mallm/discussion_paradigms/report.py
mallm/evaluation/__init__.py
mallm/evaluation/evaluator.py
mallm/evaluation/metrics/__init__.py
mallm/evaluation/metrics/bertscore.py
mallm/evaluation/metrics/bleu.py
mallm/evaluation/metrics/ifeval.py
mallm/evaluation/metrics/meteor.py
mallm/evaluation/metrics/metric.py
mallm/evaluation/metrics/qa.py
mallm/evaluation/metrics/rouge.py
mallm/evaluation/plotting/__init__.py
mallm/evaluation/plotting/plots.py
mallm/models/Chat.py
mallm/models/__init__.py
mallm/models/discussion/CriticalResponseGenerator.py
mallm/models/discussion/FreeTextResponseGenerator.py
mallm/models/discussion/ReasoningResponseGenerator.py
mallm/models/discussion/ResponseGenerator.py
mallm/models/discussion/SimpleResponseGenerator.py
mallm/models/discussion/SplitFreeTextResponseGenerator.py
mallm/models/discussion/__init__.py
mallm/models/personas/ExpertGenerator.py
mallm/models/personas/IPIPPersonaGenerator.py
mallm/models/personas/MockGenerator.py
mallm/models/personas/NoPersonaGenerator.py
mallm/models/personas/PersonaGenerator.py
mallm/models/personas/__init__.py
mallm/scheduler.py
mallm/scripts/__init__.py
mallm/scripts/batch.json.template
mallm/scripts/batch_mallm.py
mallm/utils/CustomFormatter.py
mallm-1.0.5.dist-info/LICENSE
mallm-1.0.5.dist-info/METADATA
mallm-1.0.5.dist-info/WHEEL
mallm-1.0.5.dist-info/entry_points.txt
mallm-1.0.5.dist-info/RECORD
