Metadata-Version: 2.1
Name: mallm
Version: 1.0.5
Summary: Multi-Agent Large Language Models for Collaborative Task-Solving.
License: Apache-2.0
Author: GippLab
Author-email: projects@gipplab.org
Requires-Python: >=3.9,<4.0
Classifier: License :: OSI Approved :: Apache Software License
Classifier: Operating System :: OS Independent
Classifier: Programming Language :: Python :: 3
Classifier: Programming Language :: Python :: 3.9
Classifier: Programming Language :: Python :: 3.10
Classifier: Programming Language :: Python :: 3.11
Classifier: Programming Language :: Python :: 3.12
Requires-Dist: bert-score (>=0.3.13,<0.4.0)
Requires-Dist: cffi (>=1.16.0,<2.0.0)
Requires-Dist: colorama (>=0.4.6,<0.5.0)
Requires-Dist: contextplus (>=0.1.3,<0.2.0)
Requires-Dist: datasets (>=2.18.0,<3.0.0)
Requires-Dist: evaluate (>=0.4.2,<0.5.0)
Requires-Dist: fire (>=0.6.0,<0.7.0)
Requires-Dist: huggingface-hub (==0.23.0)
Requires-Dist: immutabledict (>=4.2.0,<5.0.0)
Requires-Dist: json-repair (>=0.25.1,<0.26.0)
Requires-Dist: langchain (>=0.1.16,<0.2.0)
Requires-Dist: langchain-core (>=0.1.42,<0.2.0)
Requires-Dist: langdetect (>=1.0.9,<2.0.0)
Requires-Dist: nltk (>=3.8.1,<4.0.0)
Requires-Dist: openai (>=1.25.0,<2.0.0)
Requires-Dist: requests (>=2.32.2,<3.0.0)
Requires-Dist: rich (>=13.7.1,<14.0.0)
Requires-Dist: rouge-score (>=0.1.2,<0.2.0)
Requires-Dist: seaborn (>=0.13.2,<0.14.0)
Requires-Dist: tqdm (>=4.66.2,<5.0.0)
